README.txt
setup.py
tle2spk/__init__.py
tle2spk/tle2spk.py
tle2spk.egg-info/PKG-INFO
tle2spk.egg-info/SOURCES.txt
tle2spk.egg-info/dependency_links.txt
tle2spk.egg-info/requires.txt
tle2spk.egg-info/top_level.txt