Metadata-Version: 1.2
Name: tle2spk
Version: 0.4
Summary: Convert from Two Line Elements to binary .spk kernel
Home-page: UNKNOWN
Author: Alfredo Escalante
Author-email: alfredoescalante95@gmail.com
License: UNKNOWN
Platform: UNKNOWN
Requires-Python: >=3
